{
  "generated": "2026-07-09T23:07:42Z",
  "customer_count": 15,
  "customers": [
    {
      "customer_group": "C1",
      "segment": "resi",
      "acquisition_date": "2016-01-01",
      "fuels": [
        "electricity",
        "gas"
      ],
      "legs": {
        "electricity": {
          "cid": "C1",
          "commodity": "electricity",
          "segment": "resi",
          "acquisition_date": "2016-01-01",
          "revenue_gbp": 3545.7,
          "gross_gbp": 2343.42,
          "capital_gbp": 14.11,
          "net_gbp": 416.71,
          "cost_to_serve_gbp": 274.94,
          "total_kwh": 23558.0,
          "avg_rate_gbp_per_mwh": 150.51,
          "bill_count": 60
        },
        "gas": {
          "cid": "C1g",
          "commodity": "gas",
          "segment": "resi",
          "acquisition_date": "2016-01-01",
          "revenue_gbp": 2436.42,
          "gross_gbp": 1355.24,
          "capital_gbp": 15.79,
          "net_gbp": 669.14,
          "cost_to_serve_gbp": 5.73,
          "total_kwh": 68678.0,
          "avg_rate_gbp_per_mwh": 35.48,
          "bill_count": 60
        }
      },
      "combined": {
        "revenue_gbp": 5982.12,
        "gross_gbp": 3698.66,
        "capital_gbp": 29.9,
        "net_gbp": 1085.85,
        "cost_to_serve_gbp": 280.67,
        "total_kwh": 92236.0
      }
    },
    {
      "customer_group": "C1_2",
      "segment": "resi",
      "acquisition_date": "2016-01-01",
      "fuels": [
        "electricity"
      ],
      "legs": {
        "electricity": {
          "cid": "C1_2",
          "commodity": "electricity",
          "segment": "resi",
          "acquisition_date": "2016-01-01",
          "revenue_gbp": 11629.61,
          "gross_gbp": 5662.82,
          "capital_gbp": 81.65,
          "net_gbp": 647.97,
          "cost_to_serve_gbp": 244.19,
          "total_kwh": 43769.0,
          "avg_rate_gbp_per_mwh": 265.71,
          "bill_count": 55
        }
      },
      "combined": {
        "revenue_gbp": 11629.61,
        "gross_gbp": 5662.82,
        "capital_gbp": 81.65,
        "net_gbp": 647.97,
        "cost_to_serve_gbp": 244.19,
        "total_kwh": 43769.0
      }
    },
    {
      "customer_group": "C2",
      "segment": "resi",
      "acquisition_date": "2016-04-01",
      "fuels": [
        "electricity",
        "gas"
      ],
      "legs": {
        "electricity": {
          "cid": "C2",
          "commodity": "electricity",
          "segment": "resi",
          "acquisition_date": "2016-04-01",
          "revenue_gbp": 5110.49,
          "gross_gbp": 3412.3,
          "capital_gbp": 24.74,
          "net_gbp": 182.83,
          "cost_to_serve_gbp": 329.93,
          "total_kwh": 31666.0,
          "avg_rate_gbp_per_mwh": 161.39,
          "bill_count": 72
        },
        "gas": {
          "cid": "C2g",
          "commodity": "gas",
          "segment": "resi",
          "acquisition_date": "2016-04-01",
          "revenue_gbp": 3849.77,
          "gross_gbp": 2019.21,
          "capital_gbp": 21.85,
          "net_gbp": 907.09,
          "cost_to_serve_gbp": 6.87,
          "total_kwh": 111346.0,
          "avg_rate_gbp_per_mwh": 34.57,
          "bill_count": 72
        }
      },
      "combined": {
        "revenue_gbp": 8960.26,
        "gross_gbp": 5431.51,
        "capital_gbp": 46.59,
        "net_gbp": 1089.92,
        "cost_to_serve_gbp": 336.8,
        "total_kwh": 143012.0
      }
    },
    {
      "customer_group": "C2_2",
      "segment": "resi",
      "acquisition_date": "2016-04-01",
      "fuels": [
        "electricity"
      ],
      "legs": {
        "electricity": {
          "cid": "C2_2",
          "commodity": "electricity",
          "segment": "resi",
          "acquisition_date": "2016-04-01",
          "revenue_gbp": 10296.64,
          "gross_gbp": 5488.67,
          "capital_gbp": 67.88,
          "net_gbp": 1550.53,
          "cost_to_serve_gbp": 175.5,
          "total_kwh": 31920.0,
          "avg_rate_gbp_per_mwh": 322.57,
          "bill_count": 40
        }
      },
      "combined": {
        "revenue_gbp": 10296.64,
        "gross_gbp": 5488.67,
        "capital_gbp": 67.88,
        "net_gbp": 1550.53,
        "cost_to_serve_gbp": 175.5,
        "total_kwh": 31920.0
      }
    },
    {
      "customer_group": "C3",
      "segment": "resi",
      "acquisition_date": "2016-07-01",
      "fuels": [
        "electricity",
        "gas"
      ],
      "legs": {
        "electricity": {
          "cid": "C3",
          "commodity": "electricity",
          "segment": "resi",
          "acquisition_date": "2016-07-01",
          "revenue_gbp": 3628.86,
          "gross_gbp": 2388.97,
          "capital_gbp": 14.77,
          "net_gbp": 16.62,
          "cost_to_serve_gbp": 219.95,
          "total_kwh": 27869.0,
          "avg_rate_gbp_per_mwh": 130.21,
          "bill_count": 48
        },
        "gas": {
          "cid": "C3g",
          "commodity": "gas",
          "segment": "resi",
          "acquisition_date": "2016-07-01",
          "revenue_gbp": 2683.32,
          "gross_gbp": 1298.53,
          "capital_gbp": 15.29,
          "net_gbp": 336.46,
          "cost_to_serve_gbp": 4.58,
          "total_kwh": 96509.0,
          "avg_rate_gbp_per_mwh": 27.8,
          "bill_count": 48
        }
      },
      "combined": {
        "revenue_gbp": 6312.18,
        "gross_gbp": 3687.5,
        "capital_gbp": 30.06,
        "net_gbp": 353.08,
        "cost_to_serve_gbp": 224.53,
        "total_kwh": 124378.0
      }
    },
    {
      "customer_group": "C4",
      "segment": "resi",
      "acquisition_date": "2016-10-01",
      "fuels": [
        "electricity",
        "gas"
      ],
      "legs": {
        "electricity": {
          "cid": "C4",
          "commodity": "electricity",
          "segment": "resi",
          "acquisition_date": "2016-10-01",
          "revenue_gbp": 6193.82,
          "gross_gbp": 3242.7,
          "capital_gbp": 37.58,
          "net_gbp": 124.53,
          "cost_to_serve_gbp": 439.89,
          "total_kwh": 31861.0,
          "avg_rate_gbp_per_mwh": 194.4,
          "bill_count": 96
        },
        "gas": {
          "cid": "C4g",
          "commodity": "gas",
          "segment": "resi",
          "acquisition_date": "2016-10-01",
          "revenue_gbp": 10370.3,
          "gross_gbp": 1343.97,
          "capital_gbp": 144.75,
          "net_gbp": -1625.13,
          "cost_to_serve_gbp": 9.17,
          "total_kwh": 259743.0,
          "avg_rate_gbp_per_mwh": 39.93,
          "bill_count": 96
        }
      },
      "combined": {
        "revenue_gbp": 16564.12,
        "gross_gbp": 4586.67,
        "capital_gbp": 182.33,
        "net_gbp": -1500.6,
        "cost_to_serve_gbp": 449.06,
        "total_kwh": 291604.0
      }
    },
    {
      "customer_group": "C5",
      "segment": "SME",
      "acquisition_date": "2016-01-01",
      "fuels": [
        "electricity"
      ],
      "legs": {
        "electricity": {
          "cid": "C5",
          "commodity": "electricity",
          "segment": "SME",
          "acquisition_date": "2016-01-01",
          "revenue_gbp": 12492.19,
          "gross_gbp": 7827.61,
          "capital_gbp": 57.77,
          "net_gbp": -386.61,
          "cost_to_serve_gbp": 599.87,
          "total_kwh": 91041.0,
          "avg_rate_gbp_per_mwh": 137.21,
          "bill_count": 60
        }
      },
      "combined": {
        "revenue_gbp": 12492.19,
        "gross_gbp": 7827.61,
        "capital_gbp": 57.77,
        "net_gbp": -386.61,
        "cost_to_serve_gbp": 599.87,
        "total_kwh": 91041.0
      }
    },
    {
      "customer_group": "C6",
      "segment": "SME",
      "acquisition_date": "2016-04-01",
      "fuels": [
        "electricity"
      ],
      "legs": {
        "electricity": {
          "cid": "C6",
          "commodity": "electricity",
          "segment": "SME",
          "acquisition_date": "2016-04-01",
          "revenue_gbp": 38936.32,
          "gross_gbp": 22449.85,
          "capital_gbp": 264.31,
          "net_gbp": 3214.61,
          "cost_to_serve_gbp": 959.77,
          "total_kwh": 188037.0,
          "avg_rate_gbp_per_mwh": 207.07,
          "bill_count": 96
        }
      },
      "combined": {
        "revenue_gbp": 38936.32,
        "gross_gbp": 22449.85,
        "capital_gbp": 264.31,
        "net_gbp": 3214.61,
        "cost_to_serve_gbp": 959.77,
        "total_kwh": 188037.0
      }
    },
    {
      "customer_group": "C7",
      "segment": "resi",
      "acquisition_date": "2016-01-01",
      "fuels": [
        "electricity"
      ],
      "legs": {
        "electricity": {
          "cid": "C7",
          "commodity": "electricity",
          "segment": "resi",
          "acquisition_date": "2016-01-01",
          "revenue_gbp": 21728.81,
          "gross_gbp": 10754.49,
          "capital_gbp": 139.46,
          "net_gbp": -570.11,
          "cost_to_serve_gbp": 519.13,
          "total_kwh": 120839.0,
          "avg_rate_gbp_per_mwh": 179.82,
          "bill_count": 114
        }
      },
      "combined": {
        "revenue_gbp": 21728.81,
        "gross_gbp": 10754.49,
        "capital_gbp": 139.46,
        "net_gbp": -570.11,
        "cost_to_serve_gbp": 519.13,
        "total_kwh": 120839.0
      }
    },
    {
      "customer_group": "C8",
      "segment": "resi",
      "acquisition_date": "2016-04-01",
      "fuels": [
        "electricity"
      ],
      "legs": {
        "electricity": {
          "cid": "C8",
          "commodity": "electricity",
          "segment": "resi",
          "acquisition_date": "2016-04-01",
          "revenue_gbp": 21687.0,
          "gross_gbp": 12467.13,
          "capital_gbp": 134.9,
          "net_gbp": 2328.56,
          "cost_to_serve_gbp": 505.43,
          "total_kwh": 106722.0,
          "avg_rate_gbp_per_mwh": 203.21,
          "bill_count": 111
        }
      },
      "combined": {
        "revenue_gbp": 21687.0,
        "gross_gbp": 12467.13,
        "capital_gbp": 134.9,
        "net_gbp": 2328.56,
        "cost_to_serve_gbp": 505.43,
        "total_kwh": 106722.0
      }
    },
    {
      "customer_group": "C9",
      "segment": "resi",
      "acquisition_date": "2016-07-01",
      "fuels": [
        "electricity"
      ],
      "legs": {
        "electricity": {
          "cid": "C9",
          "commodity": "electricity",
          "segment": "resi",
          "acquisition_date": "2016-07-01",
          "revenue_gbp": 20243.59,
          "gross_gbp": 12708.07,
          "capital_gbp": 131.43,
          "net_gbp": 2239.82,
          "cost_to_serve_gbp": 491.72,
          "total_kwh": 109387.0,
          "avg_rate_gbp_per_mwh": 185.06,
          "bill_count": 108
        }
      },
      "combined": {
        "revenue_gbp": 20243.59,
        "gross_gbp": 12708.07,
        "capital_gbp": 131.43,
        "net_gbp": 2239.82,
        "cost_to_serve_gbp": 491.72,
        "total_kwh": 109387.0
      }
    },
    {
      "customer_group": "C_IC1",
      "segment": "I&C",
      "acquisition_date": "2017-01-01",
      "fuels": [
        "electricity"
      ],
      "legs": {
        "electricity": {
          "cid": "C_IC1",
          "commodity": "electricity",
          "segment": "I&C",
          "acquisition_date": "2017-01-01",
          "revenue_gbp": 3123594.92,
          "gross_gbp": 1874657.16,
          "capital_gbp": 18414.22,
          "net_gbp": 846423.33,
          "cost_to_serve_gbp": 4218.12,
          "total_kwh": 16697165.0,
          "avg_rate_gbp_per_mwh": 187.07,
          "bill_count": 102
        }
      },
      "combined": {
        "revenue_gbp": 3123594.92,
        "gross_gbp": 1874657.16,
        "capital_gbp": 18414.22,
        "net_gbp": 846423.33,
        "cost_to_serve_gbp": 4218.12,
        "total_kwh": 16697165.0
      }
    },
    {
      "customer_group": "C_IC2",
      "segment": "I&C",
      "acquisition_date": "2018-01-01",
      "fuels": [
        "electricity"
      ],
      "legs": {
        "electricity": {
          "cid": "C_IC2",
          "commodity": "electricity",
          "segment": "I&C",
          "acquisition_date": "2018-01-01",
          "revenue_gbp": 1525242.03,
          "gross_gbp": 909802.68,
          "capital_gbp": 8527.39,
          "net_gbp": 435789.37,
          "cost_to_serve_gbp": 3718.18,
          "total_kwh": 7383110.0,
          "avg_rate_gbp_per_mwh": 206.59,
          "bill_count": 90
        }
      },
      "combined": {
        "revenue_gbp": 1525242.03,
        "gross_gbp": 909802.68,
        "capital_gbp": 8527.39,
        "net_gbp": 435789.37,
        "cost_to_serve_gbp": 3718.18,
        "total_kwh": 7383110.0
      }
    },
    {
      "customer_group": "C_IC3",
      "segment": "I&C",
      "acquisition_date": "2019-01-01",
      "fuels": [
        "electricity",
        "gas"
      ],
      "legs": {
        "electricity": {
          "cid": "C_IC3",
          "commodity": "electricity",
          "segment": "I&C",
          "acquisition_date": "2019-01-01",
          "revenue_gbp": 4629967.8,
          "gross_gbp": 1825101.37,
          "capital_gbp": 23102.71,
          "net_gbp": 136684.97,
          "cost_to_serve_gbp": 3218.32,
          "total_kwh": 25608044.0,
          "avg_rate_gbp_per_mwh": 180.8,
          "bill_count": 78
        },
        "gas": {
          "cid": "C_IC3g",
          "commodity": "gas",
          "segment": "I&C",
          "acquisition_date": "2019-01-01",
          "revenue_gbp": 1832579.91,
          "gross_gbp": 622647.03,
          "capital_gbp": 0.0,
          "net_gbp": 64510.98,
          "cost_to_serve_gbp": 67.07,
          "total_kwh": 32255490.0,
          "avg_rate_gbp_per_mwh": 56.81,
          "bill_count": 78
        }
      },
      "combined": {
        "revenue_gbp": 6462547.71,
        "gross_gbp": 2447748.4,
        "capital_gbp": 23102.71,
        "net_gbp": 201195.95,
        "cost_to_serve_gbp": 3285.39,
        "total_kwh": 57863534.0
      }
    },
    {
      "customer_group": "C_IC4",
      "segment": "I&C",
      "acquisition_date": "2020-01-01",
      "fuels": [
        "electricity"
      ],
      "legs": {
        "electricity": {
          "cid": "C_IC4",
          "commodity": "electricity",
          "segment": "I&C",
          "acquisition_date": "2020-01-01",
          "revenue_gbp": 2744638.87,
          "gross_gbp": 1106685.27,
          "capital_gbp": 0.0,
          "net_gbp": 32220.65,
          "cost_to_serve_gbp": 2718.52,
          "total_kwh": 16110324.0,
          "avg_rate_gbp_per_mwh": 170.37,
          "bill_count": 66
        }
      },
      "combined": {
        "revenue_gbp": 2744638.87,
        "gross_gbp": 1106685.27,
        "capital_gbp": 0.0,
        "net_gbp": 32220.65,
        "cost_to_serve_gbp": 2718.52,
        "total_kwh": 16110324.0
      }
    }
  ]
}